gpyrobotstxt/__init__.py
gpyrobotstxt/match.py
gpyrobotstxt/parsedrobotskey.py
gpyrobotstxt/robots_cc.py
gpyrobotstxt/robotsmatchstrategy.py
gpyrobotstxt/robotstxtparser.py
gpyrobotstxt-1.0.0.dist-info/LICENSE.txt
gpyrobotstxt-1.0.0.dist-info/METADATA
gpyrobotstxt-1.0.0.dist-info/WHEEL
gpyrobotstxt-1.0.0.dist-info/top_level.txt
gpyrobotstxt-1.0.0.dist-info/RECORD
