Metadata-Version: 2.1
Name: gpyrobotstxt
Version: 1.0.0
Summary: A pure Python port of Google's robots.txt parser and matcher
Home-page: https://github.com/Cocon-Se/gpyrobotstxt
Author: CoconSe
Author-email: CoconSe <blog@cocon.se>
Project-URL: Homepage, https://github.com/Cocon-Se/gpyrobotstxt
Project-URL: Issues, https://github.com/Cocon-Se/gpyrobotstxt/issues
Classifier: Programming Language :: Python :: 3.9
Classifier: License :: OSI Approved :: GNU General Public License v3 (GPLv3)
Classifier: Operating System :: OS Independent
Requires-Python: >=3.9
License-File: LICENSE.txt
